README.md
setup.py
reclib/__init__.py
reclib/version.py
reclib.egg-info/PKG-INFO
reclib.egg-info/SOURCES.txt
reclib.egg-info/dependency_links.txt
reclib.egg-info/requires.txt
reclib.egg-info/top_level.txt