Metadata-Version: 2.1
Name: reclib
Version: 0.2.8
Summary: A Python Library for Recommender System
Home-page: https://github.com/tingkai-zhang/reclib
Author: Tingkai Zhang
Author-email: tingkai.zhang@outlook.com
License: UNKNOWN
Keywords: recommender-system,machine-learning,deep-learning
Platform: UNKNOWN
Requires-Python: >=3.6
